<environmentvariabledefinition schemaname="chub_EnvVarReviewHubDevOpsQueryID">
  <description default="The query id for the Azure DevOps work items query for Feature Requests and Scorecard Onboarding">
    <label description="The query id for the Azure DevOps work items query for Feature Requests and Scorecard Onboarding" languagecode="1033" />
  </description>
  <displayname default="EnvVar - ReviewHub - DevOps QueryID">
    <label description="EnvVar - ReviewHub - DevOps QueryID" languagecode="1033" />
  </displayname>
  <introducedversion>1.0.0.12082022</introducedversion>
  <iscustomizable>1</iscustomizable>
  <isrequired>0</isrequired>
  <secretstore>0</secretstore>
  <type>100000000</type>
</environmentvariabledefinition>